cloogy/__init__.py
cloogy/asyncclient.py
cloogy/client.py
cloogy/tag.py
cloogy/unit.py
cloogy-0.1.0.dist-info/LICENSE
cloogy-0.1.0.dist-info/METADATA
cloogy-0.1.0.dist-info/WHEEL
cloogy-0.1.0.dist-info/top_level.txt
cloogy-0.1.0.dist-info/RECORD
