Metadata-Version: 2.1
Name: cloogy
Version: 0.1.0
Summary: A python API Client for Cloogy
Home-page: https://github.com/energieid/cloogy
Author: EnergieID.be
Author-email: jan@energieid.be
License: MIT
Keywords: cloogy data monitoring api
Platform: UNKNOWN
Classifier: Development Status :: 3 - Alpha
Classifier: Intended Audience :: Developers
Classifier: Topic :: Scientific/Engineering
Classifier: License :: OSI Approved :: MIT License
Classifier: Programming Language :: Python :: 3
Classifier: Programming Language :: Python :: 3.2
Classifier: Programming Language :: Python :: 3.3
Classifier: Programming Language :: Python :: 3.4
Classifier: Programming Language :: Python :: 3.5
Classifier: Programming Language :: Python :: 3.6
Requires-Dist: requests
Requires-Dist: pandas
Requires-Dist: aiohttp
